odoo/addons/partner_identification_gln/README.rst
odoo/addons/partner_identification_gln/__init__.py
odoo/addons/partner_identification_gln/__manifest__.py
odoo/addons/partner_identification_gln/data/partner_identification_gln.xml
odoo/addons/partner_identification_gln/i18n/es.po
odoo/addons/partner_identification_gln/i18n/it.po
odoo/addons/partner_identification_gln/i18n/partner_identification_gln.pot
odoo/addons/partner_identification_gln/i18n/sl.po
odoo/addons/partner_identification_gln/models/__init__.py
odoo/addons/partner_identification_gln/models/res_partner_id_category.py
odoo/addons/partner_identification_gln/readme/CONTRIBUTORS.md
odoo/addons/partner_identification_gln/readme/CREDITS.md
odoo/addons/partner_identification_gln/readme/DESCRIPTION.md
odoo/addons/partner_identification_gln/readme/INSTALL.md
odoo/addons/partner_identification_gln/static/description/icon.svg
odoo/addons/partner_identification_gln/static/description/index.html
odoo/addons/partner_identification_gln/tests/__init__.py
odoo/addons/partner_identification_gln/tests/test_gln.py
odoo_addon_partner_identification_gln-18.0.1.0.0.3.dist-info/METADATA
odoo_addon_partner_identification_gln-18.0.1.0.0.3.dist-info/WHEEL
odoo_addon_partner_identification_gln-18.0.1.0.0.3.dist-info/top_level.txt
odoo_addon_partner_identification_gln-18.0.1.0.0.3.dist-info/RECORD
