Metadata-Version: 2.1
Name: odoo-addon-partner_identification_gln
Version: 18.0.1.0.0.3
Requires-Python: >=3.10
Requires-Dist: odoo-addon-partner_identification==18.0.*
Requires-Dist: odoo==18.0.*
Summary: This addon extends "Partner Identification Numbers" to provide a number category for GLN registration
Home-page: https://github.com/OCA/partner-contact
License: AGPL-3
Author: Acsone S.A.,Odoo Community Association (OCA)
Author-email: support@odoo-community.org
Classifier: Programming Language :: Python
Classifier: Framework :: Odoo
Classifier: Framework :: Odoo :: 18.0
Classifier: License :: OSI Approved :: GNU Affero General Public License v3
